myintegracion
