Metadata-Version: 2.1
Name: myintegracion
Version: 0.3
Summary: integracion numerica de ecuaciones diferenciales
Home-page: https://pypi.org/project/myintegracion
Author: emanuel
Author-email: emanuelnorenag@gmail.com
License: MIT
Keywords: integegracion ecuaciones diferenciales relatividad
Platform: UNKNOWN
Classifier: Programming Language :: Python :: 3
Classifier: License :: OSI Approved :: MIT License
Classifier: Operating System :: OS Independent
License-File: LICENSE
